{"3765319664":{"level":5,"nation":"usa","type":"Destroyer","name":"Hill","price":400,"date":1605037505},"3760109552":{"level":9,"nation":"usa","type":"Cruiser","name":"Alaska","price":200,"date":1605368705},"4183701456":{"level":6,"nation":"uk","type":"Destroyer","name":"Icarus","price":200,"date":1603914305},"4188976592":{"level":1,"nation":"ussr","type":"Cruiser","name":"\u041e\u0440\u043b\u0430\u043d","price":1400,"date":1603118705},"4079891920":{"level":5,"nation":"ussr","type":"Destroyer","name":"\u041f\u043e\u0434\u0432\u043e\u0439\u0441\u043a\u0438\u0439","price":1500,"date":1603752305},"4181669616":{"level":8,"nation":"italy","type":"Battleship","name":"Vittorio Veneto","price":300,"date":1604857505},"4259264496":{"level":6,"nation":"usa","type":"Battleship","name":"New Mexico","price":900,"date":1605131105},"4078876624":{"level":6,"nation":"uk","type":"Cruiser","name":"Devonshire","price":700,"date":1603572305},"3751753168":{"level":8,"nation":"ussr","type":"Battleship","name":"\u041b\u0435\u043d\u0438\u043d","price":1000,"date":1604587505},"4293834192":{"level":3,"nation":"ussr","type":"Cruiser","name":"\u0410\u0432\u0440\u043e\u0440\u0430","price":1200,"date":1604673905},"3550394352":{"level":10,"nation":"usa","type":"Cruiser","name":"Salem","price":1000,"date":1604508305},"3767449296":{"level":3,"nation":"japan","type":"Cruiser","name":"Katori","price":100,"date":1605048305},"3762206704":{"level":8,"nation":"usa","type":"Cruiser","name":"Wichita","price":1000,"date":1603043105},"3752736720":{"level":8,"nation":"uk","type":"Destroyer","name":"Cossack","price":200,"date":1603215905},"3751786480":{"level":8,"nation":"usa","type":"AirCarrier","name":"Enterprise","price":1500,"date":1605383105},"4183766768":{"level":6,"nation":"italy","type":"Battleship","name":"Andrea Doria","price":1700,"date":1602949505},"4075697872":{"level":9,"nation":"japan","type":"Destroyer","name":"Y\u016bgumo","price":400,"date":1605278705},"3332290256":{"level":8,"nation":"japan","type":"Cruiser","name":"Tone 2","price":900,"date":1604443505},"4179539920":{"level":10,"nation":"uk","type":"Cruiser","name":"Minotaur","price":1200,"date":1604241905},"4181604176":{"level":8,"nation":"france","type":"Destroyer","name":"Le\u00a0Fantasque","price":400,"date":1605465905},"4186912560":{"level":3,"nation":"germany","type":"Battleship","name":"Nassau","price":1600,"date":1602967505},"4289640144":{"level":5,"nation":"japan","type":"Cruiser","name":"Furutaka","price":700,"date":1603122305},"3742316496":{"level":7,"nation":"uk","type":"Battleship","name":"Duke of York","price":1500,"date":1605131105},"4182685648":{"level":7,"nation":"uk","type":"Cruiser","name":"Fiji","price":100,"date":1603745105},"3762173744":{"level":7,"nation":"germany","type":"Destroyer","name":"Z-39","price":500,"date":1605307505},"4293834544":{"level":1,"nation":"germany","type":"Cruiser","name":"Hermelin","price":1400,"date":1605195905},"4077795024":{"level":7,"nation":"japan","type":"Destroyer","name":"Shiratsuyu","price":200,"date":1604958305},"3763221872":{"level":7,"nation":"commonwealth","type":"Destroyer","name":"Haida","price":600,"date":1603827905},"3751786448":{"level":6,"nation":"uk","type":"AirCarrier","name":"Ark Royal","price":400,"date":1602945905},"4183799600":{"level":6,"nation":"germany","type":"AirCarrier","name":"Weser","price":2000,"date":1603043105},"3543054032":{"level":7,"nation":"japan","type":"Cruiser","name":"Southern Dragon","price":1100,"date":1603572305},"3761157584":{"level":9,"nation":"ussr","type":"Cruiser","name":"\u041a\u0440\u043e\u043d\u0448\u0442\u0430\u0434\u0442","price":100,"date":1603140305},"4179572720":{"level":10,"nation":"usa","type":"Battleship","name":"Vermont","price":1200,"date":1603557905},"3363780304":{"level":8,"nation":"japan","type":"Battleship","name":"Ragnarok","price":600,"date":1605127505},"3761190896":{"level":9,"nation":"usa","type":"Battleship","name":"Missouri","price":500,"date":1604072705},"3765384656":{"level":5,"nation":"ussr","type":"Battleship","name":"\u041e\u043a\u0442\u044f\u0431\u0440\u044c\u0441\u043a\u0430\u044f \u0440\u0435\u0432\u043e\u043b\u044e\u0446\u0438\u044f","price":1700,"date":1603730705},"4184782800":{"level":5,"nation":"uk","type":"Cruiser","name":"Emerald","price":1900,"date":1604342705},"4179572688":{"level":10,"nation":"uk","type":"Battleship","name":"Conqueror","price":1800,"date":1604349905},"3753817456":{"level":6,"nation":"commonwealth","type":"Cruiser","name":"Mysore","price":1300,"date":1604508305},"4180555056":{"level":9,"nation":"europe","type":"Destroyer","name":"\u00d6sterg\u00f6tland","price":700,"date":1603129505},"3764270832":{"level":6,"nation":"italy","type":"Destroyer","name":"Leone","price":800,"date":1602967505},"4276008656":{"level":8,"nation":"japan","type":"Cruiser","name":"Tone","price":1100,"date":1603140305},"4291770064":{"level":4,"nation":"japan","type":"Battleship","name":"My\u014dgi","price":1900,"date":1605026705},"4185798480":{"level":4,"nation":"france","type":"Destroyer","name":"Bourrasque","price":1000,"date":1605033905},"4074747856":{"level":10,"nation":"uk","type":"AirCarrier","name":"Audacious","price":1700,"date":1605296705},"4185896752":{"level":4,"nation":"germany","type":"AirCarrier","name":"Rhein","price":700,"date":1605203105},"4282267344":{"level":10,"nation":"japan","type":"Destroyer","name":"Shimakaze","price":600,"date":1603302305},"4181669328":{"level":8,"nation":"ussr","type":"Battleship","name":"\u0412\u043b\u0430\u0434\u0438\u0432\u043e\u0441\u0442\u043e\u043a","price":200,"date":1604677505},"3658397424":{"level":7,"nation":"italy","type":"Cruiser","name":"Gorizia","price":800,"date":1603205105},"3763288048":{"level":6,"nation":"usa","type":"Battleship","name":"W. Virginia 1941","price":100,"date":1605123905},"4186879952":{"level":3,"nation":"uk","type":"Cruiser","name":"Caledon","price":1900,"date":1604785505},"3761157936":{"level":9,"nation":"germany","type":"Cruiser","name":"Siegfried","price":500,"date":1603295105},"4292818736":{"level":8,"nation":"germany","type":"Battleship","name":"Tirpitz","price":1300,"date":1604781905},"3555670000":{"level":5,"nation":"usa","type":"Battleship","name":"Texas","price":1700,"date":1603118705},"3730748880":{"level":8,"nation":"ussr","type":"Cruiser","name":"\u041f\u0451\u0442\u0440 \u0411\u0430\u0433\u0440\u0430\u0442\u0438\u043e\u043d","price":200,"date":1603644305},"3762239216":{"level":8,"nation":"italy","type":"Battleship","name":"Roma","price":1500,"date":1603320305},"3760109392":{"level":10,"nation":"france","type":"Cruiser","name":"Colbert","price":300,"date":1605213905},"3668883440":{"level":7,"nation":"usa","type":"Cruiser","name":"Boise","price":1500,"date":1603640705},"4187895632":{"level":2,"nation":"france","type":"Destroyer","name":"Enseigne Gabolde","price":1700,"date":1604079905},"3445503440":{"level":10,"nation":"ussr","type":"Destroyer","name":"DD R-10","price":1200,"date":1604785505},"4183701328":{"level":6,"nation":"france","type":"Destroyer","name":"Gu\u00e9pard","price":400,"date":1604673905},"3971888592":{"level":8,"nation":"ussr","type":"Destroyer","name":"\u041a\u0438\u0435\u0432","price":1400,"date":1604425505},"3765351888":{"level":5,"nation":"ussr","type":"Cruiser","name":"\u041a\u0440\u0430\u0441\u043d\u044b\u0439 \u041a\u0440\u044b\u043c","price":1000,"date":1603305905},"3760141776":{"level":10,"nation":"ussr","type":"Battleship","name":"\u0421\u043b\u0430\u0432\u0430","price":500,"date":1603478705},"4183701200":{"level":6,"nation":"japan","type":"Destroyer","name":"Fubuki","price":1500,"date":1604853905},"3765385200":{"level":5,"nation":"usa","type":"Battleship","name":"Oklahoma","price":100,"date":1603550705},"3760175088":{"level":10,"nation":"usa","type":"AirCarrier","name":"Franklin D. Roosevelt","price":1400,"date":1603478705},"4188977104":{"level":1,"nation":"uk","type":"Cruiser","name":"Black Swan","price":1400,"date":1604961905},"4183766992":{"level":6,"nation":"uk","type":"Battleship","name":"Queen Elizabeth","price":1400,"date":1604598305},"3763255088":{"level":7,"nation":"germany","type":"Cruiser","name":"M\u00fcnchen","price":1100,"date":1605123905},"4182685520":{"level":7,"nation":"france","type":"Cruiser","name":"Alg\u00e9rie","price":2000,"date":1605393905},"4184749360":{"level":5,"nation":"europe","type":"Destroyer","name":"Visby","price":400,"date":1605393905},"4179506992":{"level":10,"nation":"germany","type":"Destroyer","name":"Z-52","price":2000,"date":1603291505},"3542005456":{"level":8,"nation":"japan","type":"Cruiser","name":"ARP Maya","price":100,"date":1602971105},"4184782672":{"level":5,"nation":"france","type":"Cruiser","name":"\u00c9mile Bertin","price":1300,"date":1604771105},"4179572560":{"level":10,"nation":"france","type":"Battleship","name":"R\u00e9publique","price":1400,"date":1604508305},"3753818064":{"level":6,"nation":"uk","type":"Cruiser","name":"London","price":100,"date":1603464305},"3764336464":{"level":6,"nation":"france","type":"Battleship","name":"Dunkerque","price":1200,"date":1603122305},"3762173136":{"level":8,"nation":"pan_asia","type":"Destroyer","name":"Loyang","price":1600,"date":1605293105},"4277024464":{"level":5,"nation":"japan","type":"Destroyer","name":"F\u016bjin","price":1500,"date":1604951105},"3767449040":{"level":3,"nation":"ussr","type":"Cruiser","name":"\u041e\u043b\u0435\u0433","price":800,"date":1604591105},"3762238928":{"level":7,"nation":"ussr","type":"Battleship","name":"\u041f\u043e\u043b\u0442\u0430\u0432\u0430","price":1600,"date":1604097905},"3552523984":{"level":5,"nation":"japan","type":"Battleship","name":"ARP Hiei","price":800,"date":1604515505},"4185864144":{"level":4,"nation":"uk","type":"Battleship","name":"Orion","price":500,"date":1604616305},"4285478160":{"level":10,"nation":"events","type":"Battleship","name":"Scorpioid","price":1000,"date":1605465905},"4186846512":{"level":3,"nation":"europe","type":"Destroyer","name":"Romulus","price":500,"date":1605123905},"4282300112":{"level":9,"nation":"japan","type":"Cruiser","name":"Ibuki","price":700,"date":1604335505},"4186879728":{"level":3,"nation":"italy","type":"Cruiser","name":"Taranto","price":1800,"date":1604591105},"3667867632":{"level":8,"nation":"usa","type":"Battleship","name":"Massachusetts B","price":1800,"date":1603395905},"4186879824":{"level":3,"nation":"france","type":"Cruiser","name":"Friant","price":800,"date":1604342705},"4181669712":{"level":8,"nation":"france","type":"Battleship","name":"Richelieu","price":1300,"date":1603493105},"3331241680":{"level":8,"nation":"japan","type":"Cruiser","name":"Tone 3","price":100,"date":1603925105},"4081039312":{"level":4,"nation":"uk","type":"AirCarrier","name":"Hermes","price":1800,"date":1603489505},"3764270288":{"level":6,"nation":"pan_asia","type":"Destroyer","name":"Anshan","price":200,"date":1603925105},"3764336432":{"level":6,"nation":"germany","type":"Battleship","name":"Prinz Eitel Friedrich","price":900,"date":1605455105},"4276041424":{"level":10,"nation":"japan","type":"Battleship","name":"Yamato","price":400,"date":1604846705},"4187894992":{"level":2,"nation":"pan_asia","type":"Destroyer","name":"Longjiang","price":700,"date":1605199505},"3762239280":{"level":8,"nation":"germany","type":"Battleship","name":"Odin","price":1600,"date":1603910705},"4077794768":{"level":7,"nation":"ussr","type":"Destroyer","name":"\u041c\u0438\u043d\u0441\u043a","price":2000,"date":1603658705},"4182718192":{"level":7,"nation":"italy","type":"Battleship","name":"Francesco Caracciolo","price":1500,"date":1605206705},"4077828080":{"level":7,"nation":"usa","type":"Cruiser","name":"Helena","price":1700,"date":1603395905},"4188976976":{"level":1,"nation":"france","type":"Cruiser","name":"Bougainville","price":100,"date":1604166305},"4183766864":{"level":6,"nation":"france","type":"Battleship","name":"Normandie","price":600,"date":1604875505},"3752802256":{"level":7,"nation":"uk","type":"Battleship","name":"Nelson","price":400,"date":1604958305},"4188976336":{"level":1,"nation":"pan_asia","type":"Cruiser","name":"Chengan","price":1400,"date":1603295105},"4179506640":{"level":10,"nation":"ussr","type":"Destroyer","name":"\u0425\u0430\u0431\u0430\u0440\u043e\u0432\u0441\u043a","price":1400,"date":1603143905},"4181669872":{"level":8,"nation":"usa","type":"Battleship","name":"Kansas","price":1800,"date":1604688305},"3374266064":{"level":8,"nation":"japan","type":"Battleship","name":"Ignis Purgatio","price":900,"date":1603575905},"4180554960":{"level":9,"nation":"pan_asia","type":"Destroyer","name":"Chung Mu","price":400,"date":1605390305},"4076779472":{"level":8,"nation":"uk","type":"Cruiser","name":"Albemarle","price":600,"date":1604335505},"4181603632":{"level":8,"nation":"europe","type":"Destroyer","name":"\u00d6land","price":1500,"date":1604173505},"4291704528":{"level":4,"nation":"japan","type":"Destroyer","name":"Isokaze","price":500,"date":1604436305},"3749623504":{"level":10,"nation":"japan","type":"Cruiser","name":"Yoshino","price":1100,"date":1604601905},"4286494416":{"level":7,"nation":"japan","type":"Cruiser","name":"My\u014dk\u014d","price":1000,"date":1603727105},"4276041712":{"level":9,"nation":"usa","type":"Battleship","name":"Iowa","price":2000,"date":1603230305},"4293834736":{"level":1,"nation":"usa","type":"Cruiser","name":"Erie","price":1700,"date":1603835105},"3760109520":{"level":10,"nation":"uk","type":"Cruiser","name":"Plymouth","price":500,"date":1604947505},"4183734000":{"level":6,"nation":"italy","type":"Cruiser","name":"Trento","price":1000,"date":1605455105},"4259231440":{"level":10,"nation":"japan","type":"Cruiser","name":"Za\u014d","price":200,"date":1603921505},"4181637104":{"level":8,"nation":"usa","type":"Cruiser","name":"Baltimore","price":1400,"date":1605375905},"3741234640":{"level":8,"nation":"ussr","type":"Cruiser","name":"\u041e\u0447\u0430\u043a\u043e\u0432","price":1300,"date":1605480305},"3766433072":{"level":5,"nation":"europe","type":"Battleship","name":"Viribus Unitis","price":1500,"date":1604425505},"4281284304":{"level":8,"nation":"japan","type":"Battleship","name":"Amagi","price":1200,"date":1604774705},"4293801680":{"level":2,"nation":"japan","type":"Destroyer","name":"Tachibana","price":400,"date":1604331905},"4288559088":{"level":7,"nation":"usa","type":"Destroyer","name":"Mahan","price":600,"date":1604695505},"4283381456":{"level":2,"nation":"japan","type":"Battleship","name":"Mikasa","price":1000,"date":1602949505},"3767416784":{"level":3,"nation":"uk","type":"Destroyer","name":"Campbeltown","price":300,"date":1604173505},"3762206672":{"level":8,"nation":"uk","type":"Cruiser","name":"Cheshire","price":500,"date":1603377905},"4180555568":{"level":9,"nation":"germany","type":"Destroyer","name":"Z-46","price":1500,"date":1603903505},"4184749776":{"level":5,"nation":"japan","type":"Destroyer","name":"Mutsuki","price":1400,"date":1605282305},"3751786192":{"level":8,"nation":"japan","type":"AirCarrier","name":"Kaga","price":1800,"date":1604177105},"4256085712":{"level":1,"nation":"japan","type":"Cruiser","name":"Hashidate","price":1900,"date":1604079905},"4183734256":{"level":6,"nation":"usa","type":"Cruiser","name":"Pensacola","price":200,"date":1603143905},"4292785968":{"level":2,"nation":"germany","type":"Cruiser","name":"Dresden","price":1600,"date":1604418305},"4181604144":{"level":8,"nation":"germany","type":"Destroyer","name":"Z-23","price":400,"date":1604526305},"3552491216":{"level":8,"nation":"japan","type":"Cruiser","name":"ARP Takao","price":900,"date":1604443505},"3767482160":{"level":3,"nation":"germany","type":"Battleship","name":"K\u00f6nig Albert","price":700,"date":1603125905},"3668916016":{"level":7,"nation":"germany","type":"Battleship","name":"Scharnhorst B","price":400,"date":1603388705},"3751687888":{"level":8,"nation":"japan","type":"Destroyer","name":"Asashio","price":600,"date":1603295105},"4185798096":{"level":4,"nation":"ussr","type":"Destroyer","name":"\u0418\u0437\u044f\u0441\u043b\u0430\u0432","price":900,"date":1604526305},"4180587984":{"level":9,"nation":"ussr","type":"Cruiser","name":"\u0414\u043c\u0438\u0442\u0440\u0438\u0439 \u0414\u043e\u043d\u0441\u043a\u043e\u0439","price":500,"date":1603125905},"3760076080":{"level":9,"nation":"europe","type":"Destroyer","name":"Friesland","price":700,"date":1604951105},"4258182864":{"level":2,"nation":"japan","type":"Cruiser","name":"Chikuma","price":1500,"date":1605372305},"4180621296":{"level":9,"nation":"usa","type":"Battleship","name":"Minnesota","price":1300,"date":1604443505},"4181702448":{"level":8,"nation":"germany","type":"AirCarrier","name":"August von Parseval","price":1800,"date":1603046705},"4183701296":{"level":6,"nation":"germany","type":"Destroyer","name":"Ernst Gaede","price":200,"date":1604789105},"3760076784":{"level":10,"nation":"usa","type":"Destroyer","name":"Somers","price":1400,"date":1604846705},"4292753392":{"level":2,"nation":"usa","type":"Destroyer","name":"Sampson","price":2000,"date":1603043105},"3756963280":{"level":3,"nation":"ussr","type":"Cruiser","name":"\u0412\u0430\u0440\u044f\u0433","price":600,"date":1604353505},"4076778960":{"level":8,"nation":"ussr","type":"Cruiser","name":"\u0422\u0430\u043b\u043b\u0438\u043d","price":200,"date":1604508305},"4187895248":{"level":2,"nation":"ussr","type":"Destroyer","name":"\u0421\u0442\u043e\u0440\u043e\u0436\u0435\u0432\u043e\u0439","price":1000,"date":1605120305},"4182685136":{"level":7,"nation":"ussr","type":"Cruiser","name":"\u0429\u043e\u0440\u0441","price":600,"date":1605285905},"3762173232":{"level":8,"nation":"europe","type":"Destroyer","name":"Orkan","price":900,"date":1605131105},"4288624336":{"level":6,"nation":"japan","type":"Battleship","name":"Fus\u014d","price":1600,"date":1604357105},"3522082512":{"level":7,"nation":"japan","type":"Cruiser","name":"ARP Nachi","price":500,"date":1603989905},"3668850672":{"level":7,"nation":"usa","type":"Destroyer","name":"Sims B","price":1700,"date":1605365105},"4185798448":{"level":4,"nation":"germany","type":"Destroyer","name":"V-170","price":1500,"date":1605465905},"4180588336":{"level":9,"nation":"germany","type":"Cruiser","name":"Roon","price":1300,"date":1604684705},"3551409616":{"level":9,"nation":"ussr","type":"Destroyer","name":"\u041d\u0435\u0443\u0441\u0442\u0440\u0430\u0448\u0438\u043c\u044b\u0439","price":100,"date":1604781905},"4284397008":{"level":2,"nation":"ussr","type":"Cruiser","name":"\u0414\u0438\u0430\u043d\u0430 Lima","price":700,"date":1604267105},"4248745968":{"level":5,"nation":"usa","type":"Cruiser","name":"Marblehead","price":1900,"date":1604342705},"3751720944":{"level":8,"nation":"usa","type":"Cruiser","name":"Anchorage","price":300,"date":1604871905},"3763222224":{"level":7,"nation":"japan","type":"Destroyer","name":"Y\u016bdachi","price":500,"date":1604335505},"4184815408":{"level":5,"nation":"germany","type":"Battleship","name":"K\u00f6nig","price":1400,"date":1604951105},"4292786160":{"level":2,"nation":"usa","type":"Cruiser","name":"Chester","price":1600,"date":1604349905},"3763288016":{"level":7,"nation":"uk","type":"Battleship","name":"Hood","price":1600,"date":1604169905},"3750639408":{"level":9,"nation":"germany","type":"Destroyer","name":"Z-44","price":1100,"date":1603651505},"3667900208":{"level":8,"nation":"germany","type":"AirCarrier","name":"Graf Zeppelin B","price":300,"date":1604958305},"4179506384":{"level":10,"nation":"pan_asia","type":"Destroyer","name":"Yueyang","price":900,"date":1604184305},"3542005744":{"level":8,"nation":"usa","type":"Cruiser","name":"AL Montpelier","price":1800,"date":1603651505},"4179572176":{"level":10,"nation":"ussr","type":"Battleship","name":"\u041a\u0440\u0435\u043c\u043b\u044c","price":1400,"date":1605278705},"4267587280":{"level":5,"nation":"japan","type":"Destroyer","name":"Kamikaze R","price":100,"date":1604339105},"4179605488":{"level":10,"nation":"usa","type":"AirCarrier","name":"Midway","price":200,"date":1603313105},"3764303696":{"level":6,"nation":"france","type":"Cruiser","name":"De Grasse","price":200,"date":1605131105},"4293867504":{"level":3,"nation":"usa","type":"Battleship","name":"South Carolina","price":1400,"date":1603896305},"4187895600":{"level":2,"nation":"germany","type":"Destroyer","name":"V-25","price":900,"date":1603403105},"4268635408":{"level":10,"nation":"events","type":"Destroyer","name":"\u041a\u043b\u044b\u043a\u043e\u0440\u0443\u043a","price":100,"date":1604079905},"3749623248":{"level":10,"nation":"ussr","type":"Cruiser","name":"\u0421\u0442\u0430\u043b\u0438\u043d\u0433\u0440\u0430\u0434 2","price":1900,"date":1602960305},"3760109264":{"level":9,"nation":"japan","type":"Cruiser","name":"Azuma","price":1700,"date":1603032305},"3553572560":{"level":5,"nation":"japan","type":"Battleship","name":"ARP Haruna","price":1800,"date":1605048305},"4286527472":{"level":7,"nation":"usa","type":"Battleship","name":"Colorado","price":800,"date":1603388705},"4290721776":{"level":4,"nation":"usa","type":"Battleship","name":"Wyoming","price":1100,"date":1603565105},"4181603536":{"level":8,"nation":"pan_asia","type":"Destroyer","name":"Hsienyang","price":1500,"date":1603467905},"4281219056":{"level":10,"nation":"usa","type":"Destroyer","name":"Gearing","price":900,"date":1603554305},"4187927824":{"level":10,"nation":"events","type":"Cruiser","name":"\u0428\u0442\u043e\u0440\u043c\u043e\u0432\u043e\u0439","price":1400,"date":1605289505},"4185863632":{"level":4,"nation":"ussr","type":"Battleship","name":"\u0413\u0430\u043d\u0433\u0443\u0442","price":500,"date":1604605505},"4186879440":{"level":3,"nation":"ussr","type":"Cruiser","name":"\u0411\u043e\u0433\u0430\u0442\u044b\u0440\u044c","price":1400,"date":1603208705},"4181636848":{"level":8,"nation":"italy","type":"Cruiser","name":"Amalfi","price":2000,"date":1603993505},"4269684432":{"level":3,"nation":"japan","type":"Destroyer","name":"Wakatake","price":1500,"date":1605469505},"4264441840":{"level":7,"nation":"usa","type":"Destroyer","name":"Sims","price":800,"date":1604699105},"3655251952":{"level":10,"nation":"usa","type":"Cruiser","name":"Puerto Rico","price":1700,"date":1604349905},"4181702640":{"level":8,"nation":"usa","type":"AirCarrier","name":"Lexington","price":1500,"date":1605473105},"4184782640":{"level":5,"nation":"germany","type":"Cruiser","name":"K\u00f6nigsberg","price":300,"date":1603813505},"4179572528":{"level":10,"nation":"germany","type":"Battleship","name":"Gro\u00dfer Kurf\u00fcrst","price":1900,"date":1605116705},"4279186704":{"level":10,"nation":"events","type":"Battleship","name":"\u041f\u0443\u0447\u0435\u0433\u043b\u0430\u0437","price":200,"date":1603748705},"4293801424":{"level":5,"nation":"ussr","type":"Destroyer","name":"\u0413\u0440\u0435\u043c\u044f\u0449\u0438\u0439","price":400,"date":1605199505},"3751720400":{"level":7,"nation":"ussr","type":"Cruiser","name":"\u041b\u0430\u0437\u043e","price":1800,"date":1604349905},"3762173936":{"level":8,"nation":"usa","type":"Destroyer","name":"Kidd","price":1100,"date":1603896305},"4293867216":{"level":3,"nation":"japan","type":"Battleship","name":"Kawachi","price":1600,"date":1604958305},"3751753712":{"level":8,"nation":"usa","type":"Battleship","name":"Massachusetts","price":1600,"date":1603914305},"4074649424":{"level":10,"nation":"france","type":"Destroyer","name":"Marceau","price":1100,"date":1604763905},"4180555728":{"level":9,"nation":"uk","type":"Destroyer","name":"Jutland","price":1900,"date":1604349905},"3767482320":{"level":3,"nation":"uk","type":"Battleship","name":"Dreadnought","price":200,"date":1602967505},"3762272208":{"level":8,"nation":"uk","type":"AirCarrier","name":"Indomitable","price":2000,"date":1603665905},"4183700688":{"level":6,"nation":"pan_asia","type":"Destroyer","name":"Fushun","price":700,"date":1605203105},"4183766480":{"level":6,"nation":"ussr","type":"Battleship","name":"\u0418\u0437\u043c\u0430\u0438\u043b","price":1600,"date":1605206705},"3667801808":{"level":8,"nation":"japan","type":"Destroyer","name":"Asashio B","price":1500,"date":1604699105},"4266538992":{"level":3,"nation":"usa","type":"Destroyer","name":"Wickes","price":1900,"date":1604695505},"4183799792":{"level":6,"nation":"usa","type":"AirCarrier","name":"Ranger","price":1200,"date":1605465905},"4075730896":{"level":9,"nation":"uk","type":"Cruiser","name":"Drake","price":200,"date":1602945905},"4186879792":{"level":3,"nation":"germany","type":"Cruiser","name":"Kolberg","price":600,"date":1603727105},"4181669680":{"level":8,"nation":"germany","type":"Battleship","name":"Bismarck","price":1000,"date":1605023105},"3764271088":{"level":6,"nation":"usa","type":"Destroyer","name":"Monaghan","price":1600,"date":1604007905},"4185864016":{"level":4,"nation":"france","type":"Battleship","name":"Courbet","price":1700,"date":1602963905},"3552524272":{"level":8,"nation":"usa","type":"Battleship","name":"Alabama ST","price":800,"date":1605037505},"3666786288":{"level":9,"nation":"usa","type":"Cruiser","name":"Alaska B","price":1700,"date":1603212305},"4182652880":{"level":7,"nation":"uk","type":"Destroyer","name":"Jervis","price":800,"date":1604871905},"3763255280":{"level":7,"nation":"usa","type":"Cruiser","name":"Indianapolis","price":1200,"date":1603302305},"3751720752":{"level":8,"nation":"germany","type":"Cruiser","name":"Mainz","price":1700,"date":1603316705},"4185797840":{"level":4,"nation":"pan_asia","type":"Destroyer","name":"Shenyang","price":200,"date":1604335505},"3865982416":{"level":9,"nation":"ussr","type":"Destroyer","name":"\u0422\u0430\u0448\u043a\u0435\u043d\u0442","price":1500,"date":1603046705},"3743364816":{"level":6,"nation":"japan","type":"Battleship","name":"Ise","price":900,"date":1604263505},"4185831152":{"level":4,"nation":"italy","type":"Cruiser","name":"Alberto di\u00a0Giussano","price":900,"date":1603817105},"4180588368":{"level":9,"nation":"france","type":"Cruiser","name":"Saint-Louis","price":300,"date":1603471505},"4077828048":{"level":7,"nation":"uk","type":"Cruiser","name":"Surrey","price":800,"date":1604774705},"4183766832":{"level":6,"nation":"germany","type":"Battleship","name":"Bayern","price":1200,"date":1603125905},"3655251408":{"level":10,"nation":"ussr","type":"Cruiser","name":"\u0421\u043c\u043e\u043b\u0435\u043d\u0441\u043a","price":1400,"date":1604688305},"4074681808":{"level":10,"nation":"ussr","type":"Cruiser","name":"\u0410\u043b\u0435\u043a\u0441\u0430\u043d\u0434\u0440 \u041d\u0435\u0432\u0441\u043a\u0438\u0439","price":1100,"date":1604155505},"4292785616":{"level":2,"nation":"ussr","type":"Cruiser","name":"\u0414\u0438\u0430\u043d\u0430","price":1100,"date":1603035905},"3761190608":{"level":9,"nation":"japan","type":"Battleship","name":"Musashi","price":2000,"date":1603226705},"4186912208":{"level":3,"nation":"ussr","type":"Battleship","name":"\u041a\u043d\u044f\u0437\u044c \u0421\u0443\u0432\u043e\u0440\u043e\u0432","price":1700,"date":1604958305},"4074649296":{"level":10,"nation":"japan","type":"Destroyer","name":"Harugumo","price":600,"date":1602945905},"3532568272":{"level":7,"nation":"japan","type":"Cruiser","name":"Eastern Dragon","price":2000,"date":1603212305},"4185798608":{"level":4,"nation":"uk","type":"Destroyer","name":"Wakeful","price":100,"date":1604443505},"4079925200":{"level":5,"nation":"uk","type":"Cruiser","name":"Hawkins","price":1900,"date":1603550705},"4180588272":{"level":9,"nation":"italy","type":"Cruiser","name":"Brindisi","price":300,"date":1604162705},"3763221968":{"level":7,"nation":"ussr","type":"Destroyer","name":"\u041b\u0435\u043d\u0438\u043d\u0433\u0440\u0430\u0434","price":700,"date":1604166305},"3551475152":{"level":9,"nation":"ussr","type":"Battleship","name":"AL \u0421\u043e\u0432. \u0420\u043e\u0441\u0441\u0438\u044f","price":600,"date":1604954705},"3750704848":{"level":9,"nation":"japan","type":"Battleship","name":"Hizen","price":900,"date":1604076305},"3768465392":{"level":2,"nation":"usa","type":"Destroyer","name":"Smith","price":600,"date":1605105905},"3763287760":{"level":7,"nation":"japan","type":"Battleship","name":"Ashitaka","price":1600,"date":1604519105},"4180588496":{"level":9,"nation":"uk","type":"Cruiser","name":"Neptune","price":200,"date":1605476705},"4186847184":{"level":3,"nation":"uk","type":"Destroyer","name":"Valkyrie","price":1300,"date":1604245505},"4181637072":{"level":8,"nation":"uk","type":"Cruiser","name":"Edinburgh","price":400,"date":1603136705},"3554588464":{"level":6,"nation":"germany","type":"Cruiser","name":"HSF Admiral Graf Spee","price":1100,"date":1604508305},"3554555600":{"level":6,"nation":"japan","type":"Destroyer","name":"Shinonome","price":200,"date":1604781905},"3765384944":{"level":5,"nation":"italy","type":"Battleship","name":"Giulio Cesare","price":1600,"date":1604432705},"4272830448":{"level":9,"nation":"usa","type":"Destroyer","name":"Fletcher","price":2000,"date":1605476705},"4181669840":{"level":8,"nation":"uk","type":"Battleship","name":"Monarch","price":500,"date":1605221105},"4182652752":{"level":7,"nation":"france","type":"Destroyer","name":"Vauquelin","price":2000,"date":1603741505},"3765319120":{"level":5,"nation":"ussr","type":"Destroyer","name":"\u041e\u0445\u043e\u0442\u043d\u0438\u043a","price":1500,"date":1604868305},"3760109008":{"level":10,"nation":"ussr","type":"Cruiser","name":"\u0421\u0442\u0430\u043b\u0438\u043d\u0433\u0440\u0430\u0434","price":1200,"date":1605023105},"3760142320":{"level":10,"nation":"usa","type":"Battleship","name":"Ohio","price":800,"date":1603478705},"4183734224":{"level":6,"nation":"uk","type":"Cruiser","name":"Leander","price":1200,"date":1603046705},"4280170192":{"level":2,"nation":"japan","type":"Destroyer","name":"Tachibana Lima","price":1100,"date":1603226705},"3655218480":{"level":10,"nation":"europe","type":"Destroyer","name":"Sm\u00e5land","price":1700,"date":1605458705},"4269717488":{"level":4,"nation":"usa","type":"Cruiser","name":"Phoenix","price":1200,"date":1602949505},"4184749904":{"level":5,"nation":"france","type":"Destroyer","name":"Jaguar","price":1800,"date":1603122305},"4179539792":{"level":10,"nation":"france","type":"Cruiser","name":"Henri IV","price":1300,"date":1605023105},"3761190096":{"level":9,"nation":"pan_asia","type":"Battleship","name":"Bajie","price":600,"date":1604180705},"3767416176":{"level":3,"nation":"commonwealth","type":"Destroyer","name":"Vampire","price":900,"date":1604594705},"3248371408":{"level":8,"nation":"japan","type":"Destroyer","name":"Arashi","price":700,"date":1604519105},"3762206160":{"level":8,"nation":"ussr","type":"Cruiser","name":"\u041c\u0438\u0445\u0430\u0438\u043b \u041a\u0443\u0442\u0443\u0437\u043e\u0432","price":2000,"date":1603395905},"4293866960":{"level":4,"nation":"ussr","type":"Battleship","name":"\u0418\u043c\u043f\u0435\u0440\u0430\u0442\u043e\u0440 \u041d\u0438\u043a\u043e\u043b\u0430\u0439 I","price":1800,"date":1604951105},"3761125104":{"level":9,"nation":"italy","type":"Destroyer","name":"Paolo Emilio","price":1200,"date":1604781905},"4186846416":{"level":3,"nation":"pan_asia","type":"Destroyer","name":"Phra Ruang","price":1200,"date":1604414705},"3762239472":{"level":8,"nation":"usa","type":"Battleship","name":"Alabama","price":1700,"date":1604515505},"4185831376":{"level":4,"nation":"uk","type":"Cruiser","name":"Danae","price":1900,"date":1604249105},"4180621264":{"level":9,"nation":"uk","type":"Battleship","name":"Lion","price":1200,"date":1605300305},"4291737584":{"level":2,"nation":"usa","type":"Cruiser","name":"Albany","price":1600,"date":1604616305},"3541972688":{"level":8,"nation":"japan","type":"Destroyer","name":"AL Yukikaze","price":1700,"date":1604774705},"3344905936":{"level":6,"nation":"japan","type":"Battleship","name":"Ise 2","price":1200,"date":1603899905},"3764303600":{"level":6,"nation":"italy","type":"Cruiser","name":"Duca d'Aosta","price":1900,"date":1604270705},"4186847056":{"level":3,"nation":"france","type":"Destroyer","name":"Fusilier","price":1000,"date":1604522705},"4181636944":{"level":8,"nation":"france","type":"Cruiser","name":"Charles Martel","price":1600,"date":1604616305},"4186912016":{"level":10,"nation":"events","type":"Battleship","name":"\u0414\u0435\u0434\u0430\u043b","price":500,"date":1603824305},"3551442640":{"level":7,"nation":"japan","type":"Cruiser","name":"ARP Haguro","price":2000,"date":1605365105},"3764303312":{"level":6,"nation":"ussr","type":"Cruiser","name":"\u041c\u043e\u043b\u043e\u0442\u043e\u0432","price":1000,"date":1603723505},"3552524016":{"level":8,"nation":"italy","type":"Battleship","name":"AL Littorio","price":600,"date":1603903505},"4290688720":{"level":4,"nation":"japan","type":"Cruiser","name":"Y\u016bbari","price":400,"date":1604263505},"4182652624":{"level":7,"nation":"japan","type":"Destroyer","name":"Akatsuki","price":700,"date":1605383105},"4182718288":{"level":7,"nation":"france","type":"Battleship","name":"Lyon","price":1100,"date":1604936705},"3764336624":{"level":6,"nation":"usa","type":"Battleship","name":"Arizona","price":200,"date":1603118705},"3741267792":{"level":8,"nation":"france","type":"Battleship","name":"Champagne","price":1900,"date":1604346305},"4187928528":{"level":2,"nation":"uk","type":"Cruiser","name":"Weymouth","price":100,"date":1604162705},"4182718416":{"level":7,"nation":"uk","type":"Battleship","name":"King George V","price":1900,"date":1604691905},"3762206512":{"level":8,"nation":"germany","type":"Cruiser","name":"Prinz Eugen","price":1900,"date":1604681105},"3751786288":{"level":8,"nation":"germany","type":"AirCarrier","name":"Graf Zeppelin","price":1700,"date":1605131105},"4180555600":{"level":9,"nation":"france","type":"Destroyer","name":"Mogador","price":500,"date":1604439905},"3340645680":{"level":10,"nation":"europe","type":"Destroyer","name":"Lappland","price":500,"date":1603392305},"4183700784":{"level":6,"nation":"europe","type":"Destroyer","name":"V\u00e4ster\u00e5s","price":100,"date":1604695505},"4279154384":{"level":3,"nation":"japan","type":"Cruiser","name":"Tenry\u016b","price":900,"date":1603752305},"4273911792":{"level":10,"nation":"usa","type":"Cruiser","name":"Des Moines","price":200,"date":1603651505},"3530504176":{"level":9,"nation":"usa","type":"Battleship","name":"Georgia","price":100,"date":1605195905},"4183734096":{"level":6,"nation":"france","type":"Cruiser","name":"La\u00a0Galissonni\u00e8re","price":300,"date":1604162705},"3769513264":{"level":7,"nation":"europe","type":"Destroyer","name":"B\u0142yskawica","price":200,"date":1602971105},"3762206544":{"level":8,"nation":"france","type":"Cruiser","name":"Bayard","price":200,"date":1603118705},"4179506480":{"level":10,"nation":"europe","type":"Destroyer","name":"Halland","price":1400,"date":1603917905},"3768497488":{"level":2,"nation":"pan_america","type":"Cruiser","name":"Almirante Abreu","price":1000,"date":1603568705},"4179605296":{"level":10,"nation":"germany","type":"AirCarrier","name":"Manfred von Richthofen","price":1100,"date":1605393905},"4184815568":{"level":5,"nation":"uk","type":"Battleship","name":"Iron Duke","price":500,"date":1605289505},"3764303664":{"level":6,"nation":"germany","type":"Cruiser","name":"Admiral Graf Spee","price":700,"date":1603136705},"3763287888":{"level":7,"nation":"france","type":"Battleship","name":"Strasbourg","price":1700,"date":1605303905},"3764303216":{"level":6,"nation":"commonwealth","type":"Cruiser","name":"Perth","price":1600,"date":1604684705},"4074649040":{"level":10,"nation":"ussr","type":"Destroyer","name":"\u0413\u0440\u043e\u0437\u043e\u0432\u043e\u0439","price":1000,"date":1602960305},"4069438928":{"level":5,"nation":"ussr","type":"Cruiser","name":"\u041a\u043e\u0442\u043e\u0432\u0441\u043a\u0438\u0439","price":1800,"date":1604267105},"4185797936":{"level":4,"nation":"europe","type":"Destroyer","name":"Klas Horn","price":1700,"date":1603723505},"3560912592":{"level":10,"nation":"japan","type":"Battleship","name":"ARP Yamato","price":700,"date":1603032305},"4281251536":{"level":4,"nation":"japan","type":"Cruiser","name":"Kuma","price":1600,"date":1605307505},"4074682352":{"level":10,"nation":"usa","type":"Cruiser","name":"Worcester","price":1500,"date":1603820705},"4185831248":{"level":4,"nation":"france","type":"Cruiser","name":"Duguay-Trouin","price":1800,"date":1603208705},"4180621136":{"level":9,"nation":"france","type":"Battleship","name":"Alsace","price":900,"date":1603302305},"4278105360":{"level":10,"nation":"events","type":"Cruiser","name":"\u0428\u0438\u043f\u043e\u0441\u043f\u0438\u043d","price":500,"date":1604526305},"4272895696":{"level":9,"nation":"japan","type":"Battleship","name":"Izumo","price":200,"date":1605123905},"4182717904":{"level":7,"nation":"ussr","type":"Battleship","name":"\u0421\u0438\u043d\u043e\u043f","price":200,"date":1604594705},"3969824208":{"level":10,"nation":"ussr","type":"Cruiser","name":"\u041f\u0435\u0442\u0440\u043e\u043f\u0430\u0432\u043b\u043e\u0432\u0441\u043a","price":1600,"date":1603320305},"3763255024":{"level":7,"nation":"italy","type":"Cruiser","name":"Duca degli Abruzzi","price":600,"date":1603896305},"4186912720":{"level":3,"nation":"uk","type":"Battleship","name":"Bellerophon","price":600,"date":1605131105},"4181702608":{"level":8,"nation":"uk","type":"AirCarrier","name":"Implacable","price":1800,"date":1603907105},"4076746448":{"level":8,"nation":"japan","type":"Destroyer","name":"Kager\u014d","price":1600,"date":1603230305},"3761190704":{"level":9,"nation":"germany","type":"Battleship","name":"Pommern","price":800,"date":1603208705},"4076746192":{"level":8,"nation":"ussr","type":"Destroyer","name":"\u041e\u0433\u043d\u0435\u0432\u043e\u0439","price":200,"date":1603395905},"3730781648":{"level":8,"nation":"ussr","type":"Battleship","name":"\u0412.\u00a0\u0418.\u00a0\u041b\u0435\u043d\u0438\u043d","price":1900,"date":1603831505},"4187895088":{"level":2,"nation":"europe","type":"Destroyer","name":"T\u00e1tra","price":1200,"date":1603122305},"3551410160":{"level":9,"nation":"usa","type":"Destroyer","name":"Black","price":600,"date":1604331905},"4076779504":{"level":8,"nation":"usa","type":"Cruiser","name":"Cleveland","price":1800,"date":1604522705},"4187928400":{"level":2,"nation":"france","type":"Cruiser","name":"Jurien de la Gravi\u00e8re","price":1900,"date":1603377905},"4182652112":{"level":7,"nation":"pan_asia","type":"Destroyer","name":"Gadjah Mada","price":1300,"date":1604785505},"3659445712":{"level":6,"nation":"ussr","type":"Cruiser","name":"\u0410\u0434\u043c\u0438\u0440\u0430\u043b \u041c\u0430\u043a\u0430\u0440\u043e\u0432","price":1300,"date":1604270705},"3754866128":{"level":5,"nation":"ussr","type":"Cruiser","name":"\u041c\u0438\u043a\u043e\u044f\u043d","price":1100,"date":1605480305},"3765352176":{"level":5,"nation":"italy","type":"Cruiser","name":"Genova","price":1600,"date":1603640705},"4188976880":{"level":1,"nation":"italy","type":"Cruiser","name":"Eritrea","price":1700,"date":1602974705},"4183799760":{"level":6,"nation":"uk","type":"AirCarrier","name":"Furious","price":2000,"date":1602963905},"3768497968":{"level":2,"nation":"germany","type":"Cruiser","name":"Emden","price":1900,"date":1603831505},"3763287856":{"level":7,"nation":"germany","type":"Battleship","name":"Scharnhorst","price":1700,"date":1603489505},"4078843344":{"level":6,"nation":"ussr","type":"Destroyer","name":"\u0413\u043d\u0435\u0432\u043d\u044b\u0439","price":1200,"date":1605375905},"3552458448":{"level":8,"nation":"japan","type":"Destroyer","name":"HSF Harekaze","price":300,"date":1603727105},"4285445840":{"level":8,"nation":"japan","type":"Cruiser","name":"Mogami","price":600,"date":1605383105},"4078876656":{"level":6,"nation":"usa","type":"Cruiser","name":"Dallas","price":600,"date":1602967505},"4184815440":{"level":5,"nation":"france","type":"Battleship","name":"Bretagne","price":1700,"date":1604861105},"3764271056":{"level":6,"nation":"uk","type":"Destroyer","name":"Gallant","price":1100,"date":1604180705},"3751720144":{"level":8,"nation":"pan_asia","type":"Cruiser","name":"Wukong","price":700,"date":1603914305},"3762205904":{"level":8,"nation":"pan_asia","type":"Cruiser","name":"Irian","price":700,"date":1604677505},"4182652208":{"level":7,"nation":"europe","type":"Destroyer","name":"Sk\u00e5ne","price":300,"date":1604529905},"4181604048":{"level":8,"nation":"japan","type":"Destroyer","name":"Akizuki","price":1100,"date":1603295105},"4180588528":{"level":9,"nation":"usa","type":"Cruiser","name":"Buffalo","price":1900,"date":1603291505},"3553540080":{"level":7,"nation":"usa","type":"Cruiser","name":"Flint","price":500,"date":1603133105},"3760174896":{"level":10,"nation":"germany","type":"AirCarrier","name":"Werner Voss","price":400,"date":1604864705},"4075730384":{"level":9,"nation":"ussr","type":"Cruiser","name":"\u0420\u0438\u0433\u0430","price":1700,"date":1605458705},"3765352144":{"level":5,"nation":"japan","type":"Cruiser","name":"Yahagi","price":600,"date":1602960305},"4292753104":{"level":2,"nation":"japan","type":"Destroyer","name":"Umikaze","price":500,"date":1602953105},"4287542992":{"level":6,"nation":"japan","type":"Cruiser","name":"Aoba","price":2000,"date":1604357105},"4277090288":{"level":10,"nation":"usa","type":"Battleship","name":"Montana","price":1100,"date":1605390305},"4186912592":{"level":3,"nation":"france","type":"Battleship","name":"Turenne","price":1200,"date":1605476705},"4292818896":{"level":6,"nation":"uk","type":"Battleship","name":"Warspite","price":1100,"date":1603143905},"4289672464":{"level":7,"nation":"events","type":"Battleship","name":"Varg","price":1200,"date":1603212305},"3764303056":{"level":6,"nation":"pan_asia","type":"Cruiser","name":"Huanghe","price":1600,"date":1603997105},"4182652368":{"level":9,"nation":"ussr","type":"Destroyer","name":"\u0423\u0434\u0430\u043b\u043e\u0439","price":1400,"date":1604429105},"3764336336":{"level":6,"nation":"japan","type":"Battleship","name":"Mutsu","price":1600,"date":1605296705},"4287575760":{"level":5,"nation":"japan","type":"Battleship","name":"Kong\u014d","price":1600,"date":1603741505},"4283381008":{"level":10,"nation":"events","type":"Battleship","name":"Crocosaur","price":1300,"date":1604875505},"3762173776":{"level":8,"nation":"france","type":"Destroyer","name":"Le Terrible","price":1300,"date":1602953105},"3751753552":{"level":9,"nation":"france","type":"Battleship","name":"Jean Bart","price":300,"date":1604011505},"3764270896":{"level":6,"nation":"germany","type":"Destroyer","name":"T-61","price":800,"date":1603219505},"3767449584":{"level":3,"nation":"usa","type":"Cruiser","name":"Charleston","price":1100,"date":1603489505},"4247697392":{"level":5,"nation":"usa","type":"Cruiser","name":"Marblehead Lima","price":800,"date":1604241905},"4289607664":{"level":6,"nation":"usa","type":"Destroyer","name":"Farragut","price":900,"date":1605365105},"4284430032":{"level":7,"nation":"japan","type":"Battleship","name":"Nagato","price":1400,"date":1604767505},"3763255248":{"level":7,"nation":"uk","type":"Cruiser","name":"Belfast","price":1000,"date":1604259905},"4182685488":{"level":7,"nation":"germany","type":"Cruiser","name":"Yorck","price":800,"date":1604443505},"3667867440":{"level":8,"nation":"germany","type":"Battleship","name":"Tirpitz B","price":1700,"date":1604421905},"4179539408":{"level":10,"nation":"ussr","type":"Cruiser","name":"\u041c\u043e\u0441\u043a\u0432\u0430","price":600,"date":1604763905},"4179605200":{"level":10,"nation":"japan","type":"AirCarrier","name":"Hakury\u016b","price":300,"date":1602945905},"3764270928":{"level":6,"nation":"france","type":"Destroyer","name":"Aigle","price":1100,"date":1603896305},"4185863984":{"level":4,"nation":"germany","type":"Battleship","name":"Kaiser","price":2000,"date":1605476705},"4182652720":{"level":7,"nation":"germany","type":"Destroyer","name":"Leberecht Maass","price":800,"date":1604349905},"3764369200":{"level":6,"nation":"germany","type":"AirCarrier","name":"Erich Loewenhardt","price":1900,"date":1605476705},"3334420176":{"level":6,"nation":"japan","type":"Battleship","name":"Ise 3","price":1600,"date":1604439905},"3744380368":{"level":5,"nation":"ussr","type":"Cruiser","name":"\u041a\u0438\u0440\u043e\u0432","price":1400,"date":1604695505},"3760076496":{"level":10,"nation":"japan","type":"Destroyer","name":"Hayate","price":500,"date":1603993505},"3553539792":{"level":7,"nation":"japan","type":"Cruiser","name":"ARP Ashigara","price":1600,"date":1604691905},"4286527184":{"level":4,"nation":"japan","type":"Battleship","name":"Ishizuchi","price":500,"date":1603903505},"4281284592":{"level":4,"nation":"usa","type":"Battleship","name":"Arkansas Beta","price":1400,"date":1605116705},"3765352400":{"level":5,"nation":"uk","type":"Cruiser","name":"Exeter","price":200,"date":1605375905},"3760142288":{"level":10,"nation":"uk","type":"Battleship","name":"Thunderer","price":1500,"date":1604331905},"3760142032":{"level":10,"nation":"japan","type":"Battleship","name":"Shikishima","price":1300,"date":1604169905},"4280170480":{"level":5,"nation":"usa","type":"Destroyer","name":"Nicholas","price":700,"date":1604954705},"4184782576":{"level":5,"nation":"italy","type":"Cruiser","name":"Raimondo Montecuccoli","price":1800,"date":1604159105},"4186846672":{"level":3,"nation":"ussr","type":"Destroyer","name":"\u0414\u0435\u0440\u0437\u043a\u0438\u0439","price":1400,"date":1603143905},"4181636560":{"level":8,"nation":"ussr","type":"Cruiser","name":"\u0427\u0430\u043f\u0430\u0435\u0432","price":1400,"date":1603205105},"3655251664":{"level":10,"nation":"japan","type":"Cruiser","name":"Kitakami","price":2000,"date":1604961905},"4184750032":{"level":5,"nation":"uk","type":"Destroyer","name":"Acasta","price":600,"date":1605372305},"4181702352":{"level":8,"nation":"japan","type":"AirCarrier","name":"Sh\u014dkaku","price":700,"date":1604004305},"3766368080":{"level":5,"nation":"france","type":"Destroyer","name":"Siroco","price":1200,"date":1605213905},"4179539760":{"level":10,"nation":"germany","type":"Cruiser","name":"Hindenburg","price":1600,"date":1603320305},"4078843600":{"level":6,"nation":"japan","type":"Destroyer","name":"Hatsuharu","price":1600,"date":1604684705},"4076745936":{"level":8,"nation":"pan_asia","type":"Destroyer","name":"Siliwangi","price":200,"date":1603568705},"4187928304":{"level":2,"nation":"italy","type":"Cruiser","name":"Nino Bixio","price":1200,"date":1605120305},"3741267408":{"level":8,"nation":"ussr","type":"Battleship","name":"\u0411\u043e\u0440\u043e\u0434\u0438\u043d\u043e","price":1800,"date":1604616305},"3555636944":{"level":7,"nation":"japan","type":"Cruiser","name":"ARP My\u014dk\u014d","price":1800,"date":1603403105},"4288591856":{"level":7,"nation":"usa","type":"Cruiser","name":"Atlanta","price":900,"date":1603637105},"3741300720":{"level":8,"nation":"usa","type":"AirCarrier","name":"Saipan","price":1700,"date":1602963905},"4286461936":{"level":8,"nation":"usa","type":"Destroyer","name":"Benson","price":300,"date":1605123905},"3762239440":{"level":8,"nation":"uk","type":"Battleship","name":"Vanguard","price":1700,"date":1603032305},"4183733712":{"level":6,"nation":"ussr","type":"Cruiser","name":"\u0411\u0443\u0434\u0451\u043d\u043d\u044b\u0439","price":100,"date":1603399505},"4065212112":{"level":9,"nation":"japan","type":"Destroyer","name":"Kitakaze","price":600,"date":1604691905},"4188976432":{"level":1,"nation":"europe","type":"Cruiser","name":"Gryf","price":200,"date":1603388705},"4183799504":{"level":6,"nation":"japan","type":"AirCarrier","name":"Ry\u016bj\u014d","price":1900,"date":1603388705},"4186847024":{"level":3,"nation":"germany","type":"Destroyer","name":"G-101","price":400,"date":1603489505},"4181636912":{"level":8,"nation":"germany","type":"Cruiser","name":"Admiral Hipper","price":1700,"date":1604771105},"4184749872":{"level":5,"nation":"germany","type":"Destroyer","name":"T-22","price":700,"date":1605458705},"4290689008":{"level":3,"nation":"usa","type":"Cruiser","name":"St.\u00a0Louis","price":1100,"date":1603205105},"4282333168":{"level":8,"nation":"usa","type":"Battleship","name":"North Carolina","price":600,"date":1603640705},"3762239184":{"level":8,"nation":"japan","type":"Battleship","name":"Kii","price":400,"date":1604702705},"3751687984":{"level":8,"nation":"germany","type":"Destroyer","name":"Z-35","price":1100,"date":1605300305},"4179507024":{"level":10,"nation":"france","type":"Destroyer","name":"Kl\u00e9ber","price":700,"date":1605037505},"4075730928":{"level":9,"nation":"usa","type":"Cruiser","name":"Seattle","price":1600,"date":1604097905},"4185830864":{"level":4,"nation":"ussr","type":"Cruiser","name":"\u0421\u0432\u0435\u0442\u043b\u0430\u043d\u0430","price":300,"date":1602967505},"4180620752":{"level":9,"nation":"ussr","type":"Battleship","name":"\u0421\u043e\u0432\u0435\u0442\u0441\u043a\u0438\u0439 \u0421\u043e\u044e\u0437","price":100,"date":1604684705},"4268635856":{"level":5,"nation":"japan","type":"Destroyer","name":"Kamikaze","price":1700,"date":1605105905},"4185896656":{"level":4,"nation":"japan","type":"AirCarrier","name":"H\u014dsh\u014d","price":1000,"date":1604933105},"3555669712":{"level":5,"nation":"japan","type":"Battleship","name":"ARP Kong\u014d","price":600,"date":1604259905},"3760142160":{"level":10,"nation":"france","type":"Battleship","name":"Bourgogne","price":600,"date":1603381505},"4183734064":{"level":6,"nation":"germany","type":"Cruiser","name":"N\u00fcrnberg","price":1300,"date":1603392305},"4188976400":{"level":10,"nation":"events","type":"Cruiser","name":"\u0412\u0430\u043b\u044c\u043a\u0438\u0440\u0438\u044f","price":1400,"date":1605033905},"4182685680":{"level":7,"nation":"usa","type":"Cruiser","name":"New Orleans","price":1500,"date":1604529905},"3761125360":{"level":9,"nation":"usa","type":"Destroyer","name":"Benham","price":400,"date":1605199505},"3554621136":{"level":5,"nation":"japan","type":"Battleship","name":"ARP Kirishima","price":500,"date":1603824305},"4179507152":{"level":10,"nation":"uk","type":"Destroyer","name":"Daring","price":1800,"date":1603561505},"3667834576":{"level":8,"nation":"japan","type":"Cruiser","name":"Atago B","price":800,"date":1603316705},"4187928016":{"level":2,"nation":"ussr","type":"Cruiser","name":"\u041d\u043e\u0432\u0438\u043a","price":1200,"date":1604526305},"4182685424":{"level":7,"nation":"italy","type":"Cruiser","name":"Zara","price":800,"date":1604958305},"4289640432":{"level":5,"nation":"usa","type":"Cruiser","name":"Omaha","price":800,"date":1605192305},"4185896944":{"level":4,"nation":"usa","type":"AirCarrier","name":"Langley","price":1500,"date":1605023105},"4290655952":{"level":5,"nation":"japan","type":"Destroyer","name":"Minekaze","price":1600,"date":1605131105},"3762239312":{"level":8,"nation":"france","type":"Battleship","name":"Gascogne","price":1700,"date":1602971105},"4074682320":{"level":10,"nation":"uk","type":"Cruiser","name":"Goliath","price":1200,"date":1603565105},"4185831216":{"level":4,"nation":"germany","type":"Cruiser","name":"Karlsruhe","price":1100,"date":1605192305},"4180621104":{"level":9,"nation":"germany","type":"Battleship","name":"Friedrich der Gro\u00dfe","price":900,"date":1604864705},"4274927600":{"level":4,"nation":"usa","type":"Destroyer","name":"Clemson","price":1300,"date":1604864705},"4179539696":{"level":10,"nation":"italy","type":"Cruiser","name":"Venezia","price":2000,"date":1603291505},"4255037136":{"level":8,"nation":"japan","type":"Cruiser","name":"Atago","price":2000,"date":1605296705},"3752802288":{"level":7,"nation":"usa","type":"Battleship","name":"Florida","price":1300,"date":1603824305},"4181604304":{"level":8,"nation":"uk","type":"Destroyer","name":"Lightning","price":300,"date":1603046705},"3750672176":{"level":9,"nation":"germany","type":"Cruiser","name":"\u00c4gir","price":1800,"date":1603982705},"4184749264":{"level":5,"nation":"pan_asia","type":"Destroyer","name":"Jianwei","price":1600,"date":1604861105},"4187895760":{"level":2,"nation":"uk","type":"Destroyer","name":"Medea","price":100,"date":1604522705},"4184815056":{"level":5,"nation":"ussr","type":"Battleship","name":"\u041f\u0451\u0442\u0440 \u0412\u0435\u043b\u0438\u043a\u0438\u0439","price":300,"date":1603989905},"4179572464":{"level":10,"nation":"italy","type":"Battleship","name":"Cristoforo Colombo","price":200,"date":1605386705},"4267620048":{"level":4,"nation":"japan","type":"Cruiser","name":"Iwaki Alpha","price":1700,"date":1603140305},"3763254608":{"level":7,"nation":"pan_america","type":"Cruiser","name":"Nueve de Julio","price":2000,"date":1605296705},"4288624624":{"level":5,"nation":"usa","type":"Battleship","name":"New York","price":1300,"date":1603651505},"3741235152":{"level":8,"nation":"uk","type":"Cruiser","name":"Belfast '43","price":200,"date":1603903505},"4182718256":{"level":7,"nation":"germany","type":"Battleship","name":"Gneisenau","price":400,"date":1605480305},"3553572848":{"level":7,"nation":"usa","type":"Battleship","name":"California","price":600,"date":1605393905},"4291737040":{"level":5,"nation":"ussr","type":"Cruiser","name":"\u041c\u0443\u0440\u043c\u0430\u043d\u0441\u043a","price":1800,"date":1604429105}}